mkv2mp4ui/__init__.py
mkv2mp4ui/ffmpeg_downloader.py
mkv2mp4ui/main.py
mkv2mp4ui-0.1.0.dist-info/licenses/LICENSE
mkv2mp4ui-0.1.0.dist-info/METADATA
mkv2mp4ui-0.1.0.dist-info/WHEEL
mkv2mp4ui-0.1.0.dist-info/entry_points.txt
mkv2mp4ui-0.1.0.dist-info/top_level.txt
mkv2mp4ui-0.1.0.dist-info/RECORD
