Metadata-Version: 2.4
Name: mkv2mp4ui
Version: 0.1.0
Summary: A PyQt6 GUI application for batch converting MKV files to MP4
Home-page: https://github.com/scottpeterman/mkvtomp4ui
Author: Scott Peterman
Author-email: scottpeterman@gmail.com
Project-URL: Bug Reports, https://github.com/scottpeterman/mkvtomp4ui/issues
Project-URL: Source, https://github.com/scottpeterman/mkvtomp4ui
Keywords: mkv,mp4,video,conversion,ffmpeg,gui,pyqt6,batch,converter,multimedia,video-processing
Classifier: Development Status :: 5 - Production/Stable
Classifier: Intended Audience :: End Users/Desktop
Classifier: License :: OSI Approved :: GNU General Public License v3 (GPLv3)
Classifier: Operating System :: Microsoft :: Windows
Classifier: Programming Language :: Python :: 3.10
Classifier: Programming Language :: Python :: 3.12
Requires-Python: >=3.10
License-File: LICENSE
Requires-Dist: certifi>=2025.6.15
Requires-Dist: charset-normalizer>=3.4.2
Requires-Dist: ffmpeg-python>=0.2.0
Requires-Dist: future>=1.0.0
Requires-Dist: idna>=3.10
Requires-Dist: PyQt6>=6.9.1
Requires-Dist: PyQt6-Qt6>=6.9.1
Requires-Dist: PyQt6_sip>=13.10.2
Requires-Dist: requests>=2.32.4
Requires-Dist: urllib3>=2.4.0
Dynamic: author
Dynamic: author-email
Dynamic: classifier
Dynamic: description
Dynamic: description-content-type
Dynamic: home-page
Dynamic: keywords
Dynamic: license-file
Dynamic: project-url
Dynamic: requires-dist
Dynamic: requires-python
Dynamic: summary
